{
  "indexes": [
    {
      "collectionGroup": "escala",
      "queryScope": "COLLECTION",
      "fields": [
        {
          "fieldPath": "userRef",
          "order": "ASCENDING"
        },
        {
          "fieldPath": "dia",
          "order": "ASCENDING"
        }
      ]
    }
  ],
  "fieldOverrides": [
    {
      "collectionGroup": "fcm_tokens",
      "fieldPath": "fcm_token",
      "indexes": [
        {
          "order": "ASCENDING",
          "queryScope": "COLLECTION_GROUP"
        }
      ]
    }
  ]
}